ooon/__init__.py
ooon/ooon.py
ooon-0.0.1.dist-info/LICENSE.txt
ooon-0.0.1.dist-info/METADATA
ooon-0.0.1.dist-info/WHEEL
ooon-0.0.1.dist-info/top_level.txt
ooon-0.0.1.dist-info/RECORD
