Metadata-Version: 2.1
Name: ooon
Version: 0.0.1
Summary: Libary For You To Know IF You are Online or Offline
Author: Ali Ayed
License-File: LICENSE.txt
Requires-Dist: requests
